LICENSE.txt
README.md
setup.cfg
setup.py
src/discord_py_activity/__init__.py
src/discord_py_activity/activities.py
src/discord_py_activity.egg-info/PKG-INFO
src/discord_py_activity.egg-info/SOURCES.txt
src/discord_py_activity.egg-info/dependency_links.txt
src/discord_py_activity.egg-info/requires.txt
src/discord_py_activity.egg-info/top_level.txt