Metadata-Version: 2.1
Name: discord-py-activity
Version: 1.3
Summary: A simple library that gives you access to discord activities
Home-page: https://github.com/lol123123f/Discord-activities
Author: SpaceX1919
Author-email: edgardbu@gmail.com
License: MIT
Keywords: Discord activity
Platform: UNKNOWN
License-File: LICENSE.txt
